<?xml version="1.0" encoding="UTF-8"?>
<part>
	<Author>PucelaBricks</Author>
	<Description>
		<en>Off-Road Fire Truck &amp; Fireboat</en>
		<fr>Camion de pompier tout terrain &amp; bateau de pompier</fr>
	</Description>
	<SortingKey>Car</SortingKey>
	<ImageURL>http://www.bricklink.com/OL/7213-1.jpg</ImageURL>
	<!-- The margin of this part in stud for snaping on the grid, relative to the bitmap -->
	<SnapMargin>
		<left>10</left>
		<right>6.25</right>
		<top>0</top>
		<bottom>0</bottom>
	</SnapMargin>	
	<hull>
	    <point>
	        <x>77</x>
	        <y>0</y>
	    </point>
	    <point>
	        <x>153</x>
	        <y>0</y>
	    </point>
	    <point>
	        <x>153</x>
	        <y>148</y>
	    </point>
	    <point>
	        <x>189</x>
	        <y>142</y>
	    </point>
	    <point>
	        <x>189</x>
	        <y>157</y>
	    </point>
	    <point>
	        <x>147</x>
	        <y>157</y>
	    </point>
	    <point>
	        <x>147</x>
	        <y>265</y>
	    </point>
	    <point>
	        <x>130</x>
	        <y>272</y>
	    </point>
	    <point>
	        <x>98</x>
	        <y>272</y>
	    </point>
	    <point>
	        <x>82</x>
	        <y>264</y>
	    </point>
	    <point>
	        <x>82</x>
	        <y>156</y>
	    </point>
	    <point>
	        <x>42</x>
	        <y>166</y>
	    </point>
	    <point>
	        <x>42</x>
	        <y>150</y>
	    </point>
	    <point>
	        <x>64</x>
	        <y>135</y>
	    </point>
	    <point>
	        <x>22</x>
	        <y>88</y>
	    </point>
	    <point>
	        <x>10</x>
	        <y>104</y>
	    </point>
	    <point>
	        <x>0</x>
	        <y>92</y>
	    </point>
	    <point>
	        <x>23</x>
	        <y>75</y>
	    </point>
	    <point>
	        <x>77</x>
	        <y>124</y>
	    </point>
	</hull>
</part>