<?xml version="1.0" encoding="UTF-8"?>
<part>
	<Author>Thomas Hess (rumpelmuck, scorpy63)</Author>
	<ImageURL>http://img.lugnet.com/display.cgi?set/new/upload/4996-1-1198029853.jpg</ImageURL>
	<Description>
		<de>Ferienhaus</de>
		<en>Beach House</en>
		<fr>La maison d'été</fr>
	</Description>
	<OldNameList>
	    <OldName>4996.set_option_1</OldName>
	</OldNameList>	
	<!-- The margin of this part in stud for snaping on the grid, relative to the bitmap -->
	<SnapMargin>
		<left>0</left>
		<right>0.5</right>
		<top>1</top>
		<bottom>0.5</bottom>
	</SnapMargin>
</part>