<?xml version="1.0" encoding="UTF-8"?>
<part>
	<Author>L@go</Author>
	<Description>
		<en>Vestas Windmill</en>
		<fr>Eolienne Vestas</fr>
	</Description>
	<OldNameList>
	    <OldName>4999.set</OldName>
	</OldNameList>
	<SortingKey>City</SortingKey>
	<ImageURL>http://media.peeron.com/pics/inv/setpics/4999-1.1236607758.thumb2.jpg</ImageURL>
	<!-- The margin of this part in stud for snaping on the grid, relative to the bitmap -->
	<SnapMargin>
		<left>23</left>
		<right>22</right>
		<top>7.5</top>
		<bottom>.5</bottom>
	</SnapMargin>
</part>